junit2html-31.0.4.dist-info/licenses/LICENSE
junit2htmlreport/__init__.py
junit2htmlreport/__main__.py
junit2htmlreport/case_result.py
junit2htmlreport/common.py
junit2htmlreport/matrix.py
junit2htmlreport/merge.py
junit2htmlreport/parser.py
junit2htmlreport/parserimpl.py
junit2htmlreport/render.py
junit2htmlreport/runner.py
junit2htmlreport/textutils.py
junit2htmlreport/templates/base.html
junit2htmlreport/templates/matrix.html
junit2htmlreport/templates/report.html
junit2htmlreport/templates/styles.css
junit2htmlreport/templates/dark/base.html
junit2htmlreport/templates/dark/matrix.html
junit2htmlreport/templates/dark/report.html
junit2htmlreport/templates/dark/styles.css
junit2htmlreport/templates/default/base.html
junit2htmlreport/templates/default/matrix.html
junit2htmlreport/templates/default/report.html
junit2htmlreport/templates/default/styles.css
junit2html-31.0.4.dist-info/METADATA
junit2html-31.0.4.dist-info/WHEEL
junit2html-31.0.4.dist-info/entry_points.txt
junit2html-31.0.4.dist-info/top_level.txt
junit2html-31.0.4.dist-info/RECORD
