Metadata-Version: 2.4
Name: junit2html
Version: 31.0.4
Summary: Generate HTML reports from Junit results
Home-page: https://gitlab.com/inorton/junit2html
Author: Ian Norton
Author-email: inorton@gmail.com
License: License :: OSI Approved :: MIT License
Requires-Python: >=3.8
License-File: LICENSE
Requires-Dist: jinja2>=3.0
Dynamic: license-file
